boredcharts/__init__.py
boredcharts/jinja.py
boredcharts/py.typed
boredcharts/router.py
boredcharts/utils.py
boredcharts/webapp.py
boredcharts/static/github-mark.min.svg
boredcharts/static/htmx-2.0.1.min.js
boredcharts/static/htmx-response-targets-2.0.1.min.js
boredcharts/static/tailwind.min.js
boredcharts/templates/base.html
boredcharts/templates/index.html
boredcharts/templates/report.html
bored_charts-0.13.1.dist-info/METADATA
bored_charts-0.13.1.dist-info/WHEEL
bored_charts-0.13.1.dist-info/RECORD
