Metadata-Version: 2.3
Name: bored-charts
Version: 0.13.1
Summary: Easy, minimal, PDF-able data reports with python and markdown.
Project-URL: Repository, https://github.com/oliverlambson/bored-charts.git
Project-URL: Issues, https://github.com/oliverlambson/bored-charts/issues
Author-email: Oliver Lambson <oliverlambson@gmail.com>
License-Expression: MIT
Keywords: PDF,boredcharts,chart,dashboard,graph,plotly,visualization
Classifier: Development Status :: 3 - Alpha
Classifier: Framework :: FastAPI
Classifier: Intended Audience :: Developers
Classifier: License :: OSI Approved :: MIT License
Classifier: Operating System :: OS Independent
Classifier: Programming Language :: Python :: 3
Classifier: Programming Language :: Python :: 3 :: Only
Classifier: Programming Language :: Python :: 3.12
Classifier: Programming Language :: Python :: 3.13
Classifier: Programming Language :: Python :: 3.14
Classifier: Programming Language :: Python :: Implementation :: CPython
Classifier: Programming Language :: Python :: Implementation :: PyPy
Classifier: Topic :: Internet :: WWW/HTTP
Classifier: Topic :: Software Development :: Libraries
Classifier: Typing :: Typed
Requires-Python: >=3.12
Requires-Dist: altair>=5.4.0
Requires-Dist: fastapi>=0.112.0
Requires-Dist: jinja2>=3.1.4
Requires-Dist: markdown>=3.6
Requires-Dist: markupsafe>=2.1.5
Requires-Dist: matplotlib>=3.9.2
Requires-Dist: plotly>=5.23.0
Requires-Dist: seaborn>=0.13.2
